ucefc/__init__.py
ucefc/core.py
ucefc/__metadata__/DISCLIAIMER.md
ucefc/__metadata__/LICENSE
ucefc/__metadata__/README.md
ucefc/__metadata__/__init__.py
ucefc/__metadata__/requirements.txt
ucefc/pkg_data/__init__.py
ucefc/pkg_data/app.py
ucefc/pkg_data/db/db.db
ucefc/pkg_data/jobs/__init__.py
ucefc/pkg_data/jobs/root.py
ucefc/pkg_data/pages/__init__.py
ucefc/pkg_data/pages/resolve.py
ucefc/pkg_data/pages/root.py
ucefc/pkg_data/root/index.css
ucefc/pkg_data/root/index.js
ucefc/pkg_data/root/robots.txt
ucefc/pkg_data/root/ucefc.css
ucefc/pkg_data/root/ucefc.html
ucefc/pkg_data/root/ucefc.js
ucefc/pkg_data/root/ucefc_api.py
ucefc-0.1.0.dist-info/METADATA
ucefc-0.1.0.dist-info/WHEEL
ucefc-0.1.0.dist-info/top_level.txt
ucefc-0.1.0.dist-info/RECORD
