Metadata-Version: 2.1
Name: ucefc
Version: 0.1.0
Summary: userscloud version of google driver encrypted folder copy.
Home-page: http://code.foxe6.kozow.com/ucefc/
Author: f̣ộx̣ệ6
Author-email: foxe6@pm.me
License: AGPL-3.0
Project-URL: Sourcecode, http://code.foxe6.kozow.com/ucefc.zip
Project-URL: Documentation, http://code.foxe6.kozow.com/ucefc/docs/
Project-URL: Example, http://code.foxe6.kozow.com/ucefc/test/
Project-URL: Funding, https://paypal.me/foxe6
Project-URL: Say Thanks!, https://saythanks.io/to/foxe6
Keywords: userscloud encrypted file copy file host clone import batch remote upload api cli manager archive
Platform: UNKNOWN
Classifier: Programming Language :: Python :: 3.9
Classifier: Topic :: Utilities
Classifier: Natural Language :: English
Classifier: Intended Audience :: Developers
Classifier: License :: OSI Approved :: GNU Affero General Public License v3
Classifier: Operating System :: MacOS
Classifier: Operating System :: POSIX
Classifier: Operating System :: Microsoft :: Windows :: Windows 10
Classifier: Development Status :: 5 - Production/Stable
Requires-Python: >=3.5
Requires-Dist: userscloud (>=0.0.1)
Requires-Dist: dwa (>=0.0.1)
Requires-Dist: ftpfcs (>=0.0.1)
